graft/__init__.py
graft/cli.py
graft/config.py
graft/decompositions.py
graft/genindices.py
graft/grad_dist.py
graft/scheduler.py
graft/trainer.py
graft/models/BERT_model.py
graft/models/MobilenetV2.py
graft/models/ResNeXt.py
graft/models/__init__.py
graft/models/efficientnet.py
graft/models/efficientnetb7.py
graft/models/fashioncnn.py
graft/models/mobilenet.py
graft/models/resnet.py
graft/models/resnet9.py
graft/utils/__init__.py
graft/utils/extras.py
graft/utils/generate.py
graft/utils/imagenetselloader.py
graft/utils/loader.py
graft/utils/model_mapper.py
graft/utils/pickler.py
graft_pytorch-1.0.0.dist-info/licenses/LICENSE
graft_pytorch-1.0.0.dist-info/METADATA
graft_pytorch-1.0.0.dist-info/WHEEL
graft_pytorch-1.0.0.dist-info/entry_points.txt
graft_pytorch-1.0.0.dist-info/top_level.txt
graft_pytorch-1.0.0.dist-info/RECORD
