Metadata-Version: 2.4
Name: graft-pytorch
Version: 1.0.0
Summary: Gradient-Aware Fast MaxVol Technique for Dynamic Data Sampling
Home-page: https://github.com/ashishjv1/GRAFT
Author: Ashish Jha, Anh Huy Phan
Author-email: Ashish Jha <Ashish.Jha@skoltech.ru>, Anh Huy Phan <a.phan@skoltech.ru>
Maintainer-email: Ashish Jha <Ashish.Jha@skoltech.ru>, Anh Huy Phan <a.phan@skoltech.ru>
License: MIT
Project-URL: Homepage, https://github.com/ashishjv1/GRAFT
Project-URL: Repository, https://github.com/ashishjv1/GRAFT
Project-URL: Bug Reports, https://github.com/ashishjv1/GRAFT/issues
Project-URL: Documentation, https://github.com/ashishjv1/GRAFT/blob/main/README.md
Keywords: machine-learning,deep-learning,pytorch,data-sampling,gradient-based-sampling
Classifier: Development Status :: 3 - Alpha
Classifier: Intended Audience :: Developers
Classifier: Intended Audience :: Science/Research
Classifier: License :: OSI Approved :: MIT License
Classifier: Operating System :: OS Independent
Classifier: Programming Language :: Python :: 3
Classifier: Programming Language :: Python :: 3.8
Classifier: Programming Language :: Python :: 3.9
Classifier: Programming Language :: Python :: 3.10
Classifier: Programming Language :: Python :: 3.11
Classifier: Topic :: Scientific/Engineering :: Artificial Intelligence
Classifier: Topic :: Software Development :: Libraries :: Python Modules
Requires-Python: >=3.8
License-File: LICENSE
Requires-Dist: torch>=1.9.0
Requires-Dist: torchvision>=0.10.0
Requires-Dist: numpy>=1.19.2
Requires-Dist: tqdm>=4.62.3
Requires-Dist: scikit-learn>=0.24.2
Requires-Dist: pillow>=8.3.1
Requires-Dist: matplotlib>=3.4.3
Requires-Dist: transformers>=4.0.0
Requires-Dist: medmnist>=2.0.0
Provides-Extra: dev
Requires-Dist: pytest>=6.2.5; extra == "dev"
Requires-Dist: pytest-cov; extra == "dev"
Requires-Dist: black; extra == "dev"
Requires-Dist: isort; extra == "dev"
Requires-Dist: flake8; extra == "dev"
Provides-Extra: tracking
Requires-Dist: wandb>=0.12.0; extra == "tracking"
Requires-Dist: eco2ai>=1.0.0; extra == "tracking"
Provides-Extra: all
Requires-Dist: pytest>=6.2.5; extra == "all"
Requires-Dist: pytest-cov; extra == "all"
Requires-Dist: black; extra == "all"
Requires-Dist: isort; extra == "all"
Requires-Dist: flake8; extra == "all"
Requires-Dist: wandb>=0.12.0; extra == "all"
Requires-Dist: eco2ai>=1.0.0; extra == "all"
Dynamic: author
Dynamic: home-page
Dynamic: license-file
Dynamic: requires-python
